mantra/__init__.py
mantra/__main__.py
mantra/ast_nodes.py
mantra/cli.py
mantra/interpreter.py
mantra/lexer.py
mantra/parser.py
mantra_lang-0.1.0.dist-info/METADATA
mantra_lang-0.1.0.dist-info/WHEEL
mantra_lang-0.1.0.dist-info/entry_points.txt
mantra_lang-0.1.0.dist-info/top_level.txt
mantra_lang-0.1.0.dist-info/RECORD
